ficture/__init__.py
ficture/cli.py
ficture/loaders/__init__.py
ficture/loaders/data_loader.py
ficture/loaders/pixel_factor_loader.py
ficture/loaders/pixel_loader.py
ficture/loaders/pixel_to_unit_loader.py
ficture/loaders/unit_loader.py
ficture/models/__init__.py
ficture/models/lda_minibatch.py
ficture/models/online_lda.py
ficture/models/online_slda.py
ficture/models/slda_minibatch.py
ficture/scripts/__init__.py
ficture/scripts/choose_color.py
ficture/scripts/de_bulk.py
ficture/scripts/factor_report.py
ficture/scripts/factor_report.template.html
ficture/scripts/filter_boundary.py
ficture/scripts/filter_density.py
ficture/scripts/filter_poly.py
ficture/scripts/init_from_pseudobulk.py
ficture/scripts/init_model_selection.py
ficture/scripts/lda_univ.py
ficture/scripts/make_dge_univ.py
ficture/scripts/make_sge_by_hexagon.py
ficture/scripts/make_spatial_minibatch.py
ficture/scripts/plot_base.py
ficture/scripts/plot_hexagon.py
ficture/scripts/plot_pixel_full.py
ficture/scripts/plot_pixel_multi.py
ficture/scripts/plot_pixel_single.py
ficture/scripts/run_together.py
ficture/scripts/slda_decode.py
ficture/scripts/transform_univ.py
ficture/utils/__init__.py
ficture/utils/filter_fn.py
ficture/utils/hexagon_fn.py
ficture/utils/image_fn.py
ficture/utils/layout_fn.py
ficture/utils/mds_color_circle.py
ficture/utils/minimake.py
ficture/utils/utilt.py
ficture/utils/visualize_factors.py
ficture-0.0.5.5.dist-info/licenses/LICENSE
ficture-0.0.5.5.dist-info/METADATA
ficture-0.0.5.5.dist-info/WHEEL
ficture-0.0.5.5.dist-info/entry_points.txt
ficture-0.0.5.5.dist-info/top_level.txt
ficture-0.0.5.5.dist-info/RECORD
