Metadata-Version: 2.4
Name: ficture
Version: 0.0.5.5
Summary: Segmentation free factor analysis for sub-micron resolution spatial transcriptomics
Author-email: Yichen Si <ycsi@umich.edu>
License: CC BY-NC 4.0
Project-URL: Homepage, https://seqscope.github.io/ficture/
Project-URL: Bug Tracker, https://github.com/seqscope/ficture/issues
Requires-Python: >=3.9
License-File: LICENSE
Requires-Dist: numpy
Requires-Dist: pandas
Requires-Dist: scipy
Requires-Dist: scikit-learn
Requires-Dist: joblib
Requires-Dist: matplotlib
Requires-Dist: Pillow
Requires-Dist: Jinja2
Requires-Dist: opencv-python
Requires-Dist: shapely
Requires-Dist: geojson
Requires-Dist: geopandas
Requires-Dist: ete3
Requires-Dist: PyQt5
Dynamic: license-file
